MANIFEST.in
README
__init__.py
__pkginfo__.py
ccplugin.py
entities.py
hooks.py
schema.py
setup.py
site_cubicweb.py
sobjects.py
uiprops.py
cubicweb_vcwiki.egg-info/PKG-INFO
cubicweb_vcwiki.egg-info/SOURCES.txt
cubicweb_vcwiki.egg-info/dependency_links.txt
cubicweb_vcwiki.egg-info/not-zip-safe
cubicweb_vcwiki.egg-info/requires.txt
cubicweb_vcwiki.egg-info/top_level.txt
data/cubes.vcwiki.css
i18n/en.po
i18n/es.po
i18n/fr.po
migration/0.2.0_Any.py
migration/postcreate.py
test/pytestconf.py
test/unittest_actions.py
test/unittest_controllers.py
test/unittest_entities.py
test/unittest_predicates.py
test/unittest_view.py
test/utils.py
views/__init__.py
views/actions.py
views/controllers.py
views/forms.py
views/uicfg.py
views/urlrewrite.py
views/wiki.py