Metadata-Version: 1.1
Name: cubicweb-vcwiki
Version: 0.4.1
Summary: Version controlled wiki component for the CubicWeb framework
Home-page: http://www.cubicweb.org/project/cubicweb-vcwiki
Author: LOGILAB S.A. (Paris, FRANCE)
Author-email: contact@logilab.fr
License: LGPL
Platform: UNKNOWN
Classifier: Environment :: Web Environment
Classifier: Framework :: CubicWeb
Classifier: Programming Language :: Python
Classifier: Programming Language :: JavaScript
